dragonfirerequests/__init__.py
dragonfirerequests/dragon.py
dragonfirerequests/response.py
dragonfirerequests-0.2.0.dist-info/METADATA
dragonfirerequests-0.2.0.dist-info/WHEEL
dragonfirerequests-0.2.0.dist-info/top_level.txt
dragonfirerequests-0.2.0.dist-info/RECORD
